Workbook

Sheet SIMULADOR
A1: SIMULADOR DE COMISSÃO — META 360 · GEREMIAS
A2: Preencha as células AMARELAS. As brancas calculam sozinhas. Tiago = EXEMPLO. Manipulação já inclui o S/N. Rentabilidade da farmácia e do funcionário pontuam se atingem a meta (aba PARÂMETROS).
B3: LARISSA | C3: MARINARA | D3: TIAGO PEREIRA | E3: Vendedor 4 | F3: Vendedor 5 | G3: FILIAL (TOTAL)
A4: ► PREENCHER — DADOS DO MÊS
A5: — Vendas por categoria (R$) —
A6: Similar
A7: Genérico
A8: Perfumaria
A9: Manipulação
A10: RX
A11: Conveniência
A12: Correlatos
A13: S/N (sem nota)
A14: Venda Total (calc) | B14: =SUM(B6:B13) -> 0 | C14: =SUM(C6:C13) -> 0 | D14: =SUM(D6:D13) -> 0 | E14: =SUM(E6:E13) -> 0 | F14: =SUM(F6:F13) -> 0 | G14: =SUM(B14:F14) -> 0
A15: Ticket Médio (R$) — opcional
A16: Desconto Médio %
A17: Rentabilidade da venda % (funcionário)
A18: Comissão paga HOJE (R$)
A19: ► PREENCHER — EQUIPE (Meta 360)
A20: Equipe: sem falta injustificada (1/0) | B20: 0
A21: Equipe: cumpriu escala/cobriu (1/0) | B21: 0
A22: Equipe: setor organizado / sem ruptura (1/0) | B22: 0
A23: Equipe: ajudou/treinou colega (1/0) | B23: 0
A24: Equipe: loja bateu meta coletiva (1/0) | B24: 0
A25: ► CÁLCULO — COMISSÃO POR CATEGORIA (R$)
A26: Com. Similar | B26: =B6*IF(B6<='PARÂMETROS'!$B$17,'PARÂMETROS'!$E$17,IF(B6<='PARÂMETROS'!$C$17,'PARÂMETROS'!$F$17,IF(B6<='PARÂMETROS'!$D$17,'PARÂMETROS'!$G$17,'PARÂMETROS'!$H$17))) -> 0 | C26: =C6*IF(C6<='PARÂMETROS'!$B$17,'PARÂMETROS'!$E$17,IF(C6<='PARÂMETROS'!$C$17,'PARÂMETROS'!$F$17,IF(C6<='PARÂMETROS'!$D$17,'PARÂMETROS'!$G$17,'PARÂMETROS'!$H$17))) -> 0 | D26: =D6*IF(D6<='PARÂMETROS'!$B$17,'PARÂMETROS'!$E$17,IF(D6<='PARÂMETROS'!$C$17,'PARÂMETROS'!$F$17,IF(D6<='PARÂMETROS'!$D$17,'PARÂMETROS'!$G$17,'PARÂMETROS'!$H$17))) -> 0 | E26: =E6*IF(E6<='PARÂMETROS'!$B$17,'PARÂMETROS'!$E$17,IF(E6<='PARÂMETROS'!$C$17,'PARÂMETROS'!$F$17,IF(E6<='PARÂMETROS'!$D$17,'PARÂMETROS'!$G$17,'PARÂMETROS'!$H$17))) -> 0 | F26: =F6*IF(F6<='PARÂMETROS'!$B$17,'PARÂMETROS'!$E$17,IF(F6<='PARÂMETROS'!$C$17,'PARÂMETROS'!$F$17,IF(F6<='PARÂMETROS'!$D$17,'PARÂMETROS'!$G$17,'PARÂMETROS'!$H$17))) -> 0
A27: Com. Genérico | B27: =B7*IF(B7<='PARÂMETROS'!$B$18,'PARÂMETROS'!$E$18,IF(B7<='PARÂMETROS'!$C$18,'PARÂMETROS'!$F$18,IF(B7<='PARÂMETROS'!$D$18,'PARÂMETROS'!$G$18,'PARÂMETROS'!$H$18))) -> 0 | C27: =C7*IF(C7<='PARÂMETROS'!$B$18,'PARÂMETROS'!$E$18,IF(C7<='PARÂMETROS'!$C$18,'PARÂMETROS'!$F$18,IF(C7<='PARÂMETROS'!$D$18,'PARÂMETROS'!$G$18,'PARÂMETROS'!$H$18))) -> 0 | D27: =D7*IF(D7<='PARÂMETROS'!$B$18,'PARÂMETROS'!$E$18,IF(D7<='PARÂMETROS'!$C$18,'PARÂMETROS'!$F$18,IF(D7<='PARÂMETROS'!$D$18,'PARÂMETROS'!$G$18,'PARÂMETROS'!$H$18))) -> 0 | E27: =E7*IF(E7<='PARÂMETROS'!$B$18,'PARÂMETROS'!$E$18,IF(E7<='PARÂMETROS'!$C$18,'PARÂMETROS'!$F$18,IF(E7<='PARÂMETROS'!$D$18,'PARÂMETROS'!$G$18,'PARÂMETROS'!$H$18))) -> 0 | F27: =F7*IF(F7<='PARÂMETROS'!$B$18,'PARÂMETROS'!$E$18,IF(F7<='PARÂMETROS'!$C$18,'PARÂMETROS'!$F$18,IF(F7<='PARÂMETROS'!$D$18,'PARÂMETROS'!$G$18,'PARÂMETROS'!$H$18))) -> 0
A28: Com. Perfumaria | B28: =B8*IF(B8<='PARÂMETROS'!$B$19,'PARÂMETROS'!$E$19,IF(B8<='PARÂMETROS'!$C$19,'PARÂMETROS'!$F$19,IF(B8<='PARÂMETROS'!$D$19,'PARÂMETROS'!$G$19,'PARÂMETROS'!$H$19))) -> 0 | C28: =C8*IF(C8<='PARÂMETROS'!$B$19,'PARÂMETROS'!$E$19,IF(C8<='PARÂMETROS'!$C$19,'PARÂMETROS'!$F$19,IF(C8<='PARÂMETROS'!$D$19,'PARÂMETROS'!$G$19,'PARÂMETROS'!$H$19))) -> 0 | D28: =D8*IF(D8<='PARÂMETROS'!$B$19,'PARÂMETROS'!$E$19,IF(D8<='PARÂMETROS'!$C$19,'PARÂMETROS'!$F$19,IF(D8<='PARÂMETROS'!$D$19,'PARÂMETROS'!$G$19,'PARÂMETROS'!$H$19))) -> 0 | E28: =E8*IF(E8<='PARÂMETROS'!$B$19,'PARÂMETROS'!$E$19,IF(E8<='PARÂMETROS'!$C$19,'PARÂMETROS'!$F$19,IF(E8<='PARÂMETROS'!$D$19,'PARÂMETROS'!$G$19,'PARÂMETROS'!$H$19))) -> 0 | F28: =F8*IF(F8<='PARÂMETROS'!$B$19,'PARÂMETROS'!$E$19,IF(F8<='PARÂMETROS'!$C$19,'PARÂMETROS'!$F$19,IF(F8<='PARÂMETROS'!$D$19,'PARÂMETROS'!$G$19,'PARÂMETROS'!$H$19))) -> 0
A29: Com. Manipulação (+ S/N) | B29: =(B9+B13)*IF((B9+B13)<='PARÂMETROS'!$B$20,'PARÂMETROS'!$E$20,IF((B9+B13)<='PARÂMETROS'!$C$20,'PARÂMETROS'!$F$20,IF((B9+B13)<='PARÂMETROS'!$D$20,'PARÂMETROS'!$G$20,'PARÂMETROS'!$H$20))) -> 0 | C29: =(C9+C13)*IF((C9+C13)<='PARÂMETROS'!$B$20,'PARÂMETROS'!$E$20,IF((C9+C13)<='PARÂMETROS'!$C$20,'PARÂMETROS'!$F$20,IF((C9+C13)<='PARÂMETROS'!$D$20,'PARÂMETROS'!$G$20,'PARÂMETROS'!$H$20))) -> 0 | D29: =(D9+D13)*IF((D9+D13)<='PARÂMETROS'!$B$20,'PARÂMETROS'!$E$20,IF((D9+D13)<='PARÂMETROS'!$C$20,'PARÂMETROS'!$F$20,IF((D9+D13)<='PARÂMETROS'!$D$20,'PARÂMETROS'!$G$20,'PARÂMETROS'!$H$20))) -> 0 | E29: =(E9+E13)*IF((E9+E13)<='PARÂMETROS'!$B$20,'PARÂMETROS'!$E$20,IF((E9+E13)<='PARÂMETROS'!$C$20,'PARÂMETROS'!$F$20,IF((E9+E13)<='PARÂMETROS'!$D$20,'PARÂMETROS'!$G$20,'PARÂMETROS'!$H$20))) -> 0 | F29: =(F9+F13)*IF((F9+F13)<='PARÂMETROS'!$B$20,'PARÂMETROS'!$E$20,IF((F9+F13)<='PARÂMETROS'!$C$20,'PARÂMETROS'!$F$20,IF((F9+F13)<='PARÂMETROS'!$D$20,'PARÂMETROS'!$G$20,'PARÂMETROS'!$H$20))) -> 0
A30: Com. RX | B30: =B10*IF(B10<='PARÂMETROS'!$B$21,'PARÂMETROS'!$E$21,IF(B10<='PARÂMETROS'!$C$21,'PARÂMETROS'!$F$21,IF(B10<='PARÂMETROS'!$D$21,'PARÂMETROS'!$G$21,'PARÂMETROS'!$H$21))) -> 0 | C30: =C10*IF(C10<='PARÂMETROS'!$B$21,'PARÂMETROS'!$E$21,IF(C10<='PARÂMETROS'!$C$21,'PARÂMETROS'!$F$21,IF(C10<='PARÂMETROS'!$D$21,'PARÂMETROS'!$G$21,'PARÂMETROS'!$H$21))) -> 0 | D30: =D10*IF(D10<='PARÂMETROS'!$B$21,'PARÂMETROS'!$E$21,IF(D10<='PARÂMETROS'!$C$21,'PARÂMETROS'!$F$21,IF(D10<='PARÂMETROS'!$D$21,'PARÂMETROS'!$G$21,'PARÂMETROS'!$H$21))) -> 0 | E30: =E10*IF(E10<='PARÂMETROS'!$B$21,'PARÂMETROS'!$E$21,IF(E10<='PARÂMETROS'!$C$21,'PARÂMETROS'!$F$21,IF(E10<='PARÂMETROS'!$D$21,'PARÂMETROS'!$G$21,'PARÂMETROS'!$H$21))) -> 0 | F30: =F10*IF(F10<='PARÂMETROS'!$B$21,'PARÂMETROS'!$E$21,IF(F10<='PARÂMETROS'!$C$21,'PARÂMETROS'!$F$21,IF(F10<='PARÂMETROS'!$D$21,'PARÂMETROS'!$G$21,'PARÂMETROS'!$H$21))) -> 0
A31: Com. Conveniência | B31: =B11*IF(B11<='PARÂMETROS'!$B$22,'PARÂMETROS'!$E$22,IF(B11<='PARÂMETROS'!$C$22,'PARÂMETROS'!$F$22,IF(B11<='PARÂMETROS'!$D$22,'PARÂMETROS'!$G$22,'PARÂMETROS'!$H$22))) -> 0 | C31: =C11*IF(C11<='PARÂMETROS'!$B$22,'PARÂMETROS'!$E$22,IF(C11<='PARÂMETROS'!$C$22,'PARÂMETROS'!$F$22,IF(C11<='PARÂMETROS'!$D$22,'PARÂMETROS'!$G$22,'PARÂMETROS'!$H$22))) -> 0 | D31: =D11*IF(D11<='PARÂMETROS'!$B$22,'PARÂMETROS'!$E$22,IF(D11<='PARÂMETROS'!$C$22,'PARÂMETROS'!$F$22,IF(D11<='PARÂMETROS'!$D$22,'PARÂMETROS'!$G$22,'PARÂMETROS'!$H$22))) -> 0 | E31: =E11*IF(E11<='PARÂMETROS'!$B$22,'PARÂMETROS'!$E$22,IF(E11<='PARÂMETROS'!$C$22,'PARÂMETROS'!$F$22,IF(E11<='PARÂMETROS'!$D$22,'PARÂMETROS'!$G$22,'PARÂMETROS'!$H$22))) -> 0 | F31: =F11*IF(F11<='PARÂMETROS'!$B$22,'PARÂMETROS'!$E$22,IF(F11<='PARÂMETROS'!$C$22,'PARÂMETROS'!$F$22,IF(F11<='PARÂMETROS'!$D$22,'PARÂMETROS'!$G$22,'PARÂMETROS'!$H$22))) -> 0
A32: Com. Correlatos | B32: =B12*IF(B12<='PARÂMETROS'!$B$23,'PARÂMETROS'!$E$23,IF(B12<='PARÂMETROS'!$C$23,'PARÂMETROS'!$F$23,IF(B12<='PARÂMETROS'!$D$23,'PARÂMETROS'!$G$23,'PARÂMETROS'!$H$23))) -> 0 | C32: =C12*IF(C12<='PARÂMETROS'!$B$23,'PARÂMETROS'!$E$23,IF(C12<='PARÂMETROS'!$C$23,'PARÂMETROS'!$F$23,IF(C12<='PARÂMETROS'!$D$23,'PARÂMETROS'!$G$23,'PARÂMETROS'!$H$23))) -> 0 | D32: =D12*IF(D12<='PARÂMETROS'!$B$23,'PARÂMETROS'!$E$23,IF(D12<='PARÂMETROS'!$C$23,'PARÂMETROS'!$F$23,IF(D12<='PARÂMETROS'!$D$23,'PARÂMETROS'!$G$23,'PARÂMETROS'!$H$23))) -> 0 | E32: =E12*IF(E12<='PARÂMETROS'!$B$23,'PARÂMETROS'!$E$23,IF(E12<='PARÂMETROS'!$C$23,'PARÂMETROS'!$F$23,IF(E12<='PARÂMETROS'!$D$23,'PARÂMETROS'!$G$23,'PARÂMETROS'!$H$23))) -> 0 | F32: =F12*IF(F12<='PARÂMETROS'!$B$23,'PARÂMETROS'!$E$23,IF(F12<='PARÂMETROS'!$C$23,'PARÂMETROS'!$F$23,IF(F12<='PARÂMETROS'!$D$23,'PARÂMETROS'!$G$23,'PARÂMETROS'!$H$23))) -> 0
A33: COMISSÃO-BASE (R$) | B33: =SUM(B26:B32) -> 0 | C33: =SUM(C26:C32) -> 0 | D33: =SUM(D26:D32) -> 0 | E33: =SUM(E26:E32) -> 0 | F33: =SUM(F26:F32) -> 0 | G33: =SUM(B33:F33) -> 0
A34: ► CÁLCULO — PONTUAÇÃO META 360 (0–100)
A35: Meta Individual (R$) | B35: ='PARÂMETROS'!B13 -> 49500 | C35: ='PARÂMETROS'!C13 -> 32500 | D35: ='PARÂMETROS'!D13 -> 29000 | E35: ='PARÂMETROS'!E13 -> 0 | F35: ='PARÂMETROS'!F13 -> 0
A36: Atingimento individual % | B36: =IFERROR(B14/B35,0) -> 0 | C36: =IFERROR(C14/C35,0) -> 0 | D36: =IFERROR(D14/D35,0) -> 0 | E36: =IFERROR(E14/E35,0) -> 0 | F36: =IFERROR(F14/F35,0) -> 0
A37: Pontos Individual (0–40) | B37: =IFERROR(VLOOKUP(B36,'PARÂMETROS'!$A$27:$B$32,2,TRUE()),0) -> 0 | C37: =IFERROR(VLOOKUP(C36,'PARÂMETROS'!$A$27:$B$32,2,TRUE()),0) -> 0 | D37: =IFERROR(VLOOKUP(D36,'PARÂMETROS'!$A$27:$B$32,2,TRUE()),0) -> 0 | E37: =IFERROR(VLOOKUP(E36,'PARÂMETROS'!$A$27:$B$32,2,TRUE()),0) -> 0 | F37: =IFERROR(VLOOKUP(F36,'PARÂMETROS'!$A$27:$B$32,2,TRUE()),0) -> 0
A38: Atingimento filial % | B38: ='PARÂMETROS'!$B$63 -> 0 | C38: ='PARÂMETROS'!$B$63 -> 0 | D38: ='PARÂMETROS'!$B$63 -> 0 | E38: ='PARÂMETROS'!$B$63 -> 0 | F38: ='PARÂMETROS'!$B$63 -> 0
A39: Pontos Filial (0–30) | B39: =IFERROR(VLOOKUP(B38,'PARÂMETROS'!$A$36:$B$39,2,TRUE()),0) -> 0 | C39: =IFERROR(VLOOKUP(C38,'PARÂMETROS'!$A$36:$B$39,2,TRUE()),0) -> 0 | D39: =IFERROR(VLOOKUP(D38,'PARÂMETROS'!$A$36:$B$39,2,TRUE()),0) -> 0 | E39: =IFERROR(VLOOKUP(E38,'PARÂMETROS'!$A$36:$B$39,2,TRUE()),0) -> 0 | F39: =IFERROR(VLOOKUP(F38,'PARÂMETROS'!$A$36:$B$39,2,TRUE()),0) -> 0
A40: Pontos Qualidade/Rentab. (0–20) | B40: 0 | C40: =MIN(20,MAX(0,MIN('PARÂMETROS'!$B$44,'PARÂMETROS'!$B$44*('PARÂMETROS'!$B$43-C16)/('PARÂMETROS'!$B$43-'PARÂMETROS'!$B$42)))+IF('PARÂMETROS'!$B$65>='PARÂMETROS'!$B$45,'PARÂMETROS'!$B$46,0)+IF(C17>='PARÂMETROS'!$B$47,'PARÂMETROS'!$B$48,0)) -> 6 | D40: =MIN(20,MAX(0,MIN('PARÂMETROS'!$B$44,'PARÂMETROS'!$B$44*('PARÂMETROS'!$B$43-D16)/('PARÂMETROS'!$B$43-'PARÂMETROS'!$B$42)))+IF('PARÂMETROS'!$B$65>='PARÂMETROS'!$B$45,'PARÂMETROS'!$B$46,0)+IF(D17>='PARÂMETROS'!$B$47,'PARÂMETROS'!$B$48,0)) -> 6 | E40: =MIN(20,MAX(0,MIN('PARÂMETROS'!$B$44,'PARÂMETROS'!$B$44*('PARÂMETROS'!$B$43-E16)/('PARÂMETROS'!$B$43-'PARÂMETROS'!$B$42)))+IF('PARÂMETROS'!$B$65>='PARÂMETROS'!$B$45,'PARÂMETROS'!$B$46,0)+IF(E17>='PARÂMETROS'!$B$47,'PARÂMETROS'!$B$48,0)) -> 6 | F40: =MIN(20,MAX(0,MIN('PARÂMETROS'!$B$44,'PARÂMETROS'!$B$44*('PARÂMETROS'!$B$43-F16)/('PARÂMETROS'!$B$43-'PARÂMETROS'!$B$42)))+IF('PARÂMETROS'!$B$65>='PARÂMETROS'!$B$45,'PARÂMETROS'!$B$46,0)+IF(F17>='PARÂMETROS'!$B$47,'PARÂMETROS'!$B$48,0)) -> 6
A41: Pontos Equipe (0–10) | B41: =MIN(10,SUM(B20:B24)*2) -> 0 | C41: =MIN(10,SUM(C20:C24)*2) -> 0 | D41: =MIN(10,SUM(D20:D24)*2) -> 0 | E41: =MIN(10,SUM(E20:E24)*2) -> 0 | F41: =MIN(10,SUM(F20:F24)*2) -> 0
A42: PONTUAÇÃO FINAL (0–100) | B42: =MIN(100,B37+B39+B40+B41) -> 0 | C42: =MIN(100,C37+C39+C40+C41) -> 6 | D42: =MIN(100,D37+D39+D40+D41) -> 6 | E42: =MIN(100,E37+E39+E40+E41) -> 6 | F42: =MIN(100,F37+F39+F40+F41) -> 6
A43: Nível | B43: =IFERROR(VLOOKUP(B42,'PARÂMETROS'!$A$52:$C$57,2,TRUE()),"") -> Em desenvolvimento | C43: =IFERROR(VLOOKUP(C42,'PARÂMETROS'!$A$52:$C$57,2,TRUE()),"") -> Em desenvolvimento | D43: =IFERROR(VLOOKUP(D42,'PARÂMETROS'!$A$52:$C$57,2,TRUE()),"") -> Em desenvolvimento | E43: =IFERROR(VLOOKUP(E42,'PARÂMETROS'!$A$52:$C$57,2,TRUE()),"") -> Em desenvolvimento | F43: =IFERROR(VLOOKUP(F42,'PARÂMETROS'!$A$52:$C$57,2,TRUE()),"") -> Em desenvolvimento
A44: Multiplicador | B44: =IFERROR(VLOOKUP(B42,'PARÂMETROS'!$A$52:$C$57,3,TRUE()),0) -> 0 | C44: =IFERROR(VLOOKUP(C42,'PARÂMETROS'!$A$52:$C$57,3,TRUE()),0) -> 0 | D44: =IFERROR(VLOOKUP(D42,'PARÂMETROS'!$A$52:$C$57,3,TRUE()),0) -> 0 | E44: =IFERROR(VLOOKUP(E42,'PARÂMETROS'!$A$52:$C$57,3,TRUE()),0) -> 0 | F44: =IFERROR(VLOOKUP(F42,'PARÂMETROS'!$A$52:$C$57,3,TRUE()),0) -> 0
A45: ► RESULTADO — COMISSÃO
A46: Comissão Ajustada (Base × Mult) | B46: =B33*B44 -> 0 | C46: =C33*C44 -> 0 | D46: =D33*D44 -> 0 | E46: =E33*E44 -> 0 | F46: =F33*F44 -> 0 | G46: =SUM(B46:F46) -> 0
A47: Prêmio Filial (R$) | B47: =IF('PARÂMETROS'!$B$63>=1,'PARÂMETROS'!$B$60,0) -> 0 | C47: =IF('PARÂMETROS'!$B$63>=1,'PARÂMETROS'!$B$60,0) -> 0 | D47: =IF('PARÂMETROS'!$B$63>=1,'PARÂMETROS'!$B$60,0) -> 0 | E47: =IF('PARÂMETROS'!$B$63>=1,'PARÂMETROS'!$B$60,0) -> 0 | F47: =IF('PARÂMETROS'!$B$63>=1,'PARÂMETROS'!$B$60,0) -> 0 | G47: =SUM(B47:F47) -> 0
A48: TOTAL COMISSÃO — Modelo Original | B48: =B46+B47 -> 0 | C48: =C46+C47 -> 0 | D48: =D46+D47 -> 0 | E48: =E46+E47 -> 0 | F48: =F46+F47 -> 0 | G48: =SUM(B48:F48) -> 0
A49: TOTAL COMISSÃO — Modelo Protegido ★ | B49: =B33*MAX(1,B44)+B47 -> 0 | C49: =C33*MAX(1,C44)+C47 -> 0 | D49: =D33*MAX(1,D44)+D47 -> 0 | E49: =E33*MAX(1,E44)+E47 -> 0 | F49: =F33*MAX(1,F44)+F47 -> 0 | G49: =SUM(B49:F49) -> 0
A51: Δ vs comissão de hoje — Original | B51: =B48-B18 -> 0 | C51: =C48-C18 -> 0 | D51: =D48-D18 -> 0 | E51: =E48-E18 -> 0 | F51: =F48-F18 -> 0 | G51: =SUM(B51:F51) -> 0
A52: Δ vs comissão de hoje — Protegido ★ | B52: =B49-B18 -> 0 | C52: =C49-C18 -> 0 | D52: =D49-D18 -> 0 | E52: =E49-E18 -> 0 | F52: =F49-F18 -> 0 | G52: =SUM(B52:F52) -> 0

Sheet PARÂMETROS
A1: PARÂMETROS DA POLÍTICA — edite as regras aqui (texto azul = editável)
A3: A. METAS INDIVIDUAIS POR CATEGORIA (R$/mês)
A4: Categoria | B4: LARISSA | C4: MARINARA | D4: TIAGO PEREIRA | E4: Vendedor 4 | F4: Vendedor 5
A5: Similar | B5: 7000 | C5: 4000 | D5: 5000 | E5: 0 | F5: 0
A6: Genérico | B6: 7400 | C6: 5000 | D6: 5500 | E6: 0 | F6: 0
A7: Perfumaria | B7: 7200 | C7: 6000 | D7: 4000 | E7: 0 | F7: 0
A8: Manipulação | B8: 8400 | C8: 5000 | D8: 4000 | E8: 0 | F8: 0
A9: RX | B9: 15000 | C9: 10000 | D9: 8000 | E9: 0 | F9: 0
A10: Conveniência | B10: 2500 | C10: 1500 | D10: 1500 | E10: 0 | F10: 0
A11: Correlatos | B11: 2000 | C11: 1000 | D11: 1000 | E11: 0 | F11: 0
A12: S/N | B12: 0 | C12: 0 | D12: 0 | E12: 0 | F12: 0
A13: Meta Individual Total | B13: =SUM(B5:B12) -> 49500 | C13: =SUM(C5:C12) -> 32500 | D13: =SUM(D5:D12) -> 29000 | E13: =SUM(E5:E12) -> 0 | F13: =SUM(F5:F12) -> 0
A15: B. TABELA DE COMISSÃO POR CATEGORIA (o % da faixa incide sobre o total vendido na categoria)
A16: Categoria | B16: Até faixa 1 (R$) | C16: Até faixa 2 (R$) | D16: Até faixa 3 (R$) | E16: % faixa 1 | F16: % faixa 2 | G16: % faixa 3 | H16: % acima
A17: Similar | B17: 3000 | C17: 7000 | D17: 10000 | E17: 0.01 | F17: 0.03 | G17: 0.04 | H17: 0.06
A18: Genérico | B18: 4000 | C18: 5800 | D18: 8000 | E18: 0.01 | F18: 0.02 | G18: 0.03 | H18: 0.05
A19: Perfumaria | B19: 4500 | C19: 8500 | D19: 10000 | E19: 0.01 | F19: 0.03 | G19: 0.04 | H19: 0.06
A20: Manipulação | B20: 5000 | C20: 8500 | D20: 15000 | E20: 0.01 | F20: 0.02 | G20: 0.04 | H20: 0.06
A21: RX | B21: 12000 | C21: 16000 | D21: 20000 | E21: 0.01 | F21: 0.02 | G21: 0.03 | H21: 0.04
A22: Conveniência | B22: 2000 | C22: 3500 | D22: 5000 | E22: 0.01 | F22: 0.02 | G22: 0.04 | H22: 0.06
A23: Correlatos | B23: 1000 | C23: 1900 | D23: 3000 | E23: 0.01 | F23: 0.02 | G23: 0.03 | H23: 0.06
A25: C. PONTOS — RESULTADO INDIVIDUAL (peso 40) · por % de atingimento da meta
A26: Atingimento ≥ | B26: Pontos
A27: 0 | B27: 0
A28: 0.7 | B28: 20
A29: 0.8 | B29: 28
A30: 0.9 | B30: 34
A31: 1 | B31: 38
A32: 1.1 | B32: 40
A34: D. PONTOS — RESULTADO FILIAL (peso 30) · por % de atingimento da filial
A35: Atingimento ≥ | B35: Pontos
A36: 0 | B36: 0
A37: 0.8 | B37: 15
A38: 0.9 | B38: 22
A39: 1 | B39: 30
A41: E. QUALIDADE / RENTABILIDADE (peso 20 = desconto 6 + rentab. farmácia 7 + rentab. funcionário 7)
A42: Desconto ≤ (pts cheios) | B42: 0.12
A43: Desconto ≥ (0 pts) | B43: 0.25
A44: Pontos máx. desconto | B44: 6
A45: Meta rentab. FARMÁCIA (%) | B45: 0.3
A46: Pontos se farmácia atinge | B46: 7
A47: Meta rentab. FUNCIONÁRIO (%) | B47: 0.28
A48: Pontos se funcionário atinge | B48: 7
A50: F. TABELA DE MULTIPLICADOR (Meta 360)
A51: Pontuação ≥ | B51: Nível | C51: Multiplicador
A52: 0 | B52: Em desenvolvimento | C52: 0
A53: 60 | B53: Bronze | C53: 0.5
A54: 70 | B54: Prata | C54: 0.75
A55: 80 | B55: Platina | C55: 1
A56: 90 | B56: Diamante | C56: 1.2
A57: 95 | B57: Ouro | C57: 1.5
A59: G. PRÊMIO E FILIAL
A60: Prêmio Meta Filial (R$) | B60: 0
A61: Meta da filial no mês (R$) | B61: 0
A62: Realizado da filial no mês (R$) | B62: 152000
A63: Atingimento da filial % | B63: =IFERROR(B62/B61,0) -> 0
A64: Filial bateu a meta? | B64: =IF(B63>=1,"SIM","NÃO") -> NÃO
A65: Rentab. REALIZADA da farmácia (%) | B65: 0

Sheet COMO USAR
A1: COMO USAR ESTE SIMULADOR
A3: 1. | B3: Preencha as células AMARELAS de cada vendedor: vendas por categoria, desconto médio, rentabilidade da venda %, comissão paga hoje e os campos de Equipe.
A4: 2. | B4: A coluna do TIAGO vem com números de EXEMPLO. Substitua pelos reais.
A5: 3. | B5: Manipulação + S/N: o S/N não passa no sistema, mas é pago junto com a manipulação. A planilha soma os dois e aplica a faixa da manipulação sobre o total.
A6: 4. | B6: Rentabilidade (novo): o pilar Qualidade/Rentabilidade (20 pts) agora é desconto (6) + rentabilidade da farmácia atingida (7) + rentabilidade do funcionário atingida (7). As metas de % e os pontos ficam na aba PARÂMETROS, seção E; a rentab. realizada da farmácia fica na seção G.
A7: 5. | B7: A planilha não trata salário nem remuneração — é só o parâmetro de comissionamento. A remuneração final (dias trabalhados etc.) é calculada na folha.
A8: 6. | B8: A coluna FILIAL (TOTAL) soma os vendedores. As linhas 'Δ vs comissão de hoje' comparam o modelo novo com o que se paga hoje — é a prova de custo.
A9: 7. | B9: Modelo Original × Protegido (★, recomendado): no Original o multiplicador incide sobre tudo. No Protegido a comissão vendida é piso e o 360 só soma por cima.
A10: 8. | B10: Para mudar qualquer regra, use a aba PARÂMETROS (textos azuis são editáveis).
